MANIFEST.in
README.md
setup.py
revenge/Colorer.py
revenge/__init__.py
revenge/config.py
revenge/exceptions.py
revenge/functions.py
revenge/native_exception.py
revenge/process.py
revenge/symbols.py
revenge/types.py
revenge.egg-info/PKG-INFO
revenge.egg-info/SOURCES.txt
revenge.egg-info/dependency_links.txt
revenge.egg-info/entry_points.txt
revenge.egg-info/requires.txt
revenge.egg-info/top_level.txt
revenge/cli/__init__.py
revenge/cli/cli.py
revenge/cli/actions/__init__.py
revenge/cli/actions/differential_find.py
revenge/cli/actions/find.py
revenge/cli/actions/stalker.py
revenge/cli/actions/windows_messages.py
revenge/common/__init__.py
revenge/common/windows_keys_by_id.json
revenge/common/windows_messages_by_id.json
revenge/common/windows_messages_by_name.json
revenge/contexts/__init__.py
revenge/contexts/batch.py
revenge/cpu/__init__.py
revenge/cpu/assembly/__init__.py
revenge/cpu/assembly/instruction.py
revenge/cpu/contexts/__init__.py
revenge/cpu/contexts/arm.py
revenge/cpu/contexts/x64.py
revenge/cpu/contexts/x86.py
revenge/devices/__init__.py
revenge/devices/android/__init__.py
revenge/devices/android/android.py
revenge/devices/android/applications.py
revenge/devices/local/__init__.py
revenge/devices/process/__init__.py
revenge/devices/process/process.py
revenge/devices/process/processes.py
revenge/engines/__init__.py
revenge/engines/frida/__init__.py
revenge/engines/frida/process.py
revenge/engines/frida/devices/__init__.py
revenge/engines/frida/devices/local_device.py
revenge/engines/frida/memory/__init__.py
revenge/engines/frida/memory/find.py
revenge/engines/frida/memory/map.py
revenge/engines/frida/memory/memory.py
revenge/engines/frida/memory/memory_bytes.py
revenge/engines/frida/memory/memory_range.py
revenge/engines/frida/plugins/__init__.py
revenge/engines/frida/plugins/angr/__init__.py
revenge/engines/frida/plugins/angr/angr.py
revenge/engines/frida/plugins/decompiler/__init__.py
revenge/engines/frida/plugins/decompiler/decompiler.py
revenge/engines/frida/plugins/dwarf/__init__.py
revenge/engines/frida/plugins/handles/__init__.py
revenge/engines/frida/plugins/handles/handles.py
revenge/engines/frida/plugins/java/__init__.py
